logistiflight/__init__.py
logistiflight/logistic_regression_module.py
logistiflight-0.0.1.dist-info/METADATA
logistiflight-0.0.1.dist-info/WHEEL
logistiflight-0.0.1.dist-info/top_level.txt
logistiflight-0.0.1.dist-info/RECORD
