Metadata-Version: 2.1
Name: logistiflight
Version: 0.0.1
Summary: 로지스틱회귀 예제 1
Home-page: UNKNOWN
Author: TaeMin
Author-email: taeminida@gmail.com
License: UNKNOWN
Platform: UNKNOWN
Requires-Python: >=3.9.13
Requires-Dist: numpy
Requires-Dist: pandas
Requires-Dist: matplotlib
Requires-Dist: seaborn
Requires-Dist: scikit-learn
Requires-Dist: dmba
Requires-Dist: mord
